package_topsis/__init__.py
package_topsis/topsis.py
package_topsis-0.3.dist-info/License.txt.txt
package_topsis-0.3.dist-info/METADATA
package_topsis-0.3.dist-info/WHEEL
package_topsis-0.3.dist-info/top_level.txt
package_topsis-0.3.dist-info/RECORD
